Workbook

Sheet clean data
A1: Sales_Order # | B1: Date | C1: Day | D1: Month | E1: Year | F1: Customer_Age | G1: Age_Group | H1: Customer_Gender | I1: Country_id | J1: Country | K1: State_id | L1: State | M1: Product_Category | N1: Sub_Category | O1: Model_id | P1: Model | Q1: Color_id | R1: Color | S1: Size | T1: Order_Quantity | U1: Unit_Cost | V1: Unit_Price | W1: Profit | X1: Cost | Y1: Revenue
A2: 261695 | B2: 44531 | C2: 1 | D2: December | E2: 2021 | F2: 39 | G2: Adults (35-64) | H2: Female | I2: =VLOOKUP('clean data'!J2:J89,country_dim!A$2:B$7,2,TRUE) -> C-106 | J2: United States | K2: =VLOOKUP(L2:L89,state_dim!A$2:B$18,2,TRUE) -> S-102 | L2: California | M2: Bikes | N2: Mountain Bikes | O2: =VLOOKUP(P2:P89,model_dim!A$2:B$5,2,TRUE) -> M-102 | P2: Mountain-200 | Q2: =VLOOKUP(R2:R89,'col-dim'!A$2:B$3,2,TRUE) -> Col-1 | R2: Black | S2: 46 | T2: 4 | U2: 1252 | V2: 2295 | W2: 4172 | X2: =T2*U2 -> 5008 | Y2: =T2*V2 -> 9180
A3: 261696 | B3: 44531 | C3: 1 | D3: December | E3: 2021 | F3: 44 | G3: Adults (35-64) | H3: Male | I3: =VLOOKUP('clean data'!J3:J90,country_dim!A$2:B$7,2,TRUE) -> C-105 | J3: United Kingdom | K3: =VLOOKUP(L3:L90,state_dim!A$2:B$18,2,TRUE) -> S-103 | L3: England | M3: Bikes | N3: Mountain Bikes | O3: =VLOOKUP(P3:P90,model_dim!A$2:B$5,2,TRUE) -> M-102 | P3: Mountain-200 | Q3: =VLOOKUP(R3:R90,'col-dim'!A$2:B$3,2,TRUE) -> Col-2 | R3: Silver | S3: 42 | T3: 1 | U3: 1266 | V3: 2320 | W3: 1054 | X3: =T3*U3 -> 1266 | Y3: =T3*V3 -> 2320
A4: 261697 | B4: 44532 | C4: 2 | D4: December | E4: 2021 | F4: 37 | G4: Adults (35-64) | H4: Male | I4: =VLOOKUP('clean data'!J4:J91,country_dim!A$2:B$7,2,TRUE) -> C-106 | J4: United States | K4: =VLOOKUP(L4:L91,state_dim!A$2:B$18,2,TRUE) -> S-102 | L4: California | M4: Bikes | N4: Mountain Bikes | O4: =VLOOKUP(P4:P91,model_dim!A$2:B$5,2,TRUE) -> M-103 | P4: Mountain-400-W | Q4: =VLOOKUP(R4:R91,'col-dim'!A$2:B$3,2,TRUE) -> Col-2 | R4: Silver | S4: 46 | T4: 2 | U4: 420 | V4: 769 | W4: 698 | X4: =T4*U4 -> 840 | Y4: =T4*V4 -> 1538
A5: 261698 | B5: 44532 | C5: 2 | D5: December | E5: 2021 | F5: 31 | G5: Young Adults (25-34) | H5: Female | I5: =VLOOKUP('clean data'!J5:J92,country_dim!A$2:B$7,2,TRUE) -> C-101 | J5: Australia | K5: =VLOOKUP(L5:L92,state_dim!A$2:B$18,2,TRUE) -> S-106 | L5: New South Wales | M5: Bikes | N5: Mountain Bikes | O5: =VLOOKUP(P5:P92,model_dim!A$2:B$5,2,TRUE) -> M-103 | P5: Mountain-400-W | Q5: =VLOOKUP(R5:R92,'col-dim'!A$2:B$3,2,TRUE) -> Col-2 | R5: Silver | S5: 42 | T5: 1 | U5: 420 | V5: 769 | W5: 349 | X5: =T5*U5 -> 420 | Y5: =T5*V5 -> 769
A6: 261699 | B6: 44533 | C6: 3 | D6: December | E6: 2021 | F6: 37 | G6: Adults (35-64) | H6: Female | I6: =VLOOKUP('clean data'!J6:J93,country_dim!A$2:B$7,2,TRUE) -> C-106 | J6: United States | K6: =VLOOKUP(L6:L93,state_dim!A$2:B$18,2,TRUE) -> S-102 | L6: California | M6: Bikes | N6: Mountain Bikes | O6: =VLOOKUP(P6:P93,model_dim!A$2:B$5,2,TRUE) -> M-102 | P6: Mountain-200 | Q6: =VLOOKUP(R6:R93,'col-dim'!A$2:B$3,2,TRUE) -> Col-1 | R6: Black | S6: 46 | T6: 2 | U6: 1252 | V6: 2295 | W6: 2086 | X6: =T6*U6 -> 2504 | Y6: =T6*V6 -> 4590
A7: 261700 | B7: 44533 | C7: 3 | D7: December | E7: 2021 | F7: 24 | G7: Youth (<25) | H7: Female | I7: =VLOOKUP('clean data'!J7:J94,country_dim!A$2:B$7,2,TRUE) -> C-105 | J7: United Kingdom | K7: =VLOOKUP(L7:L94,state_dim!A$2:B$18,2,TRUE) -> S-103 | L7: England | M7: Bikes | N7: Mountain Bikes | O7: =VLOOKUP(P7:P94,model_dim!A$2:B$5,2,TRUE) -> M-102 | P7: Mountain-200 | Q7: =VLOOKUP(R7:R94,'col-dim'!A$2:B$3,2,TRUE) -> Col-1 | R7: Black | S7: 38 | T7: 1 | U7: 1252 | V7: 2295 | W7: 1043 | X7: =T7*U7 -> 1252 | Y7: =T7*V7 -> 2295
A8: 261701 | B8: 44533 | C8: 3 | D8: December | E8: 2021 | F8: 37 | G8: Adults (35-64) | H8: Male | I8: =VLOOKUP('clean data'!J8:J95,country_dim!A$2:B$7,2,TRUE) -> C-106 | J8: United States | K8: =VLOOKUP(L8:L95,state_dim!A$2:B$18,2,TRUE) -> S-117 | L8: Washington | M8: Bikes | N8: Mountain Bikes | O8: =VLOOKUP(P8:P95,model_dim!A$2:B$5,2,TRUE) -> M-102 | P8: Mountain-200 | Q8: =VLOOKUP(R8:R95,'col-dim'!A$2:B$3,2,TRUE) -> Col-1 | R8: Black | S8: 46 | T8: 1 | U8: 1252 | V8: 2295 | W8: 1043 | X8: =T8*U8 -> 1252 | Y8: =T8*V8 -> 2295
A9: 261702 | B9: 44534 | C9: 4 | D9: December | E9: 2021 | F9: 31 | G9: Young Adults (25-34) | H9: Female | I9: =VLOOKUP('clean data'!J9:J96,country_dim!A$2:B$7,2,TRUE) -> C-101 | J9: Australia | K9: =VLOOKUP(L9:L96,state_dim!A$2:B$18,2,TRUE) -> S-106 | L9: New South Wales | M9: Bikes | N9: Mountain Bikes | O9: =VLOOKUP(P9:P96,model_dim!A$2:B$5,2,TRUE) -> M-103 | P9: Mountain-400-W | Q9: =VLOOKUP(R9:R96,'col-dim'!A$2:B$3,2,TRUE) -> Col-2 | R9: Silver | S9: 42 | T9: 4 | U9: 420 | V9: 769 | W9: 1396 | X9: =T9*U9 -> 1680 | Y9: =T9*V9 -> 3076
A10: 261703 | B10: 44535 | C10: 5 | D10: December | E10: 2021 | F10: 39 | G10: Adults (35-64) | H10: Female | I10: =VLOOKUP('clean data'!J10:J97,country_dim!A$2:B$7,2,TRUE) -> C-106 | J10: United States | K10: =VLOOKUP(L10:L97,state_dim!A$2:B$18,2,TRUE) -> S-102 | L10: California | M10: Bikes | N10: Mountain Bikes | O10: =VLOOKUP(P10:P97,model_dim!A$2:B$5,2,TRUE) -> M-102 | P10: Mountain-200 | Q10: =VLOOKUP(R10:R97,'col-dim'!A$2:B$3,2,TRUE) -> Col-1 | R10: Black | S10: 46 | T10: 4 | U10: 1252 | V10: 2295 | W10: 4172 | X10: =T10*U10 -> 5008 | Y10: =T10*V10 -> 9180
A11: 261704 | B11: 44535 | C11: 5 | D11: December | E11: 2021 | F11: 42 | G11: Adults (35-64) | H11: Male | I11: =VLOOKUP('clean data'!J11:J98,country_dim!A$2:B$7,2,TRUE) -> C-104 | J11: Germany | K11: =VLOOKUP(L11:L98,state_dim!A$2:B$18,2,TRUE) -> S-108 | L11: Nordrhein-Westfalen | M11: Bikes | N11: Mountain Bikes | O11: =VLOOKUP(P11:P98,model_dim!A$2:B$5,2,TRUE) -> M-102 | P11: Mountain-200 | Q11: =VLOOKUP(R11:R98,'col-dim'!A$2:B$3,2,TRUE) -> Col-1 | R11: Black | S11: 38 | T11: 4 | U11: 1252 | V11: 2295 | W11: 4172 | X11: =T11*U11 -> 5008 | Y11: =T11*V11 -> 9180
A12: 261705 | B12: 44535 | C12: 5 | D12: December | E12: 2021 | F12: 35 | G12: Adults (35-64) | H12: Female | I12: =VLOOKUP('clean data'!J12:J99,country_dim!A$2:B$7,2,TRUE) -> C-101 | J12: Australia | K12: =VLOOKUP(L12:L99,state_dim!A$2:B$18,2,TRUE) -> S-110 | L12: Queensland | M12: Bikes | N12: Mountain Bikes | O12: =VLOOKUP(P12:P99,model_dim!A$2:B$5,2,TRUE) -> M-102 | P12: Mountain-200 | Q12: =VLOOKUP(R12:R99,'col-dim'!A$2:B$3,2,TRUE) -> Col-2 | R12: Silver | S12: 38 | T12: 1 | U12: 1266 | V12: 2320 | W12: 1054 | X12: =T12*U12 -> 1266 | Y12: =T12*V12 -> 2320
A13: 261706 | B13: 44535 | C13: 5 | D13: December | E13: 2021 | F13: 37 | G13: Adults (35-64) | H13: Female | I13: =VLOOKUP('clean data'!J13:J100,country_dim!A$2:B$7,2,TRUE) -> C-106 | J13: United States | K13: =VLOOKUP(L13:L100,state_dim!A$2:B$18,2,TRUE) -> S-102 | L13: California | M13: Bikes | N13: Mountain Bikes | O13: =VLOOKUP(P13:P100,model_dim!A$2:B$5,2,TRUE) -> M-102 | P13: Mountain-200 | Q13: =VLOOKUP(R13:R100,'col-dim'!A$2:B$3,2,TRUE) -> Col-1 | R13: Black | S13: 46 | T13: 1 | U13: 1252 | V13: 2295 | W13: 1043 | X13: =T13*U13 -> 1252 | Y13: =T13*V13 -> 2295
... A89: 261782 | B89: 44554 | C89: 24 | D89: December | E89: 2021 | F89: 38 | G89: Adults (35-64) | H89: Male | I89: =VLOOKUP('clean data'!J89:J176,country_dim!A$2:B$7,2,TRUE) -> C-101 | J89: Australia | K89: =VLOOKUP(L89:L176,state_dim!A$2:B$18,2,TRUE) -> S-110 | L89: Queensland | M89: Bikes | N89: Mountain Bikes | O89: =VLOOKUP(P89:P176,model_dim!A$2:B$5,2,TRUE) -> M-102 | P89: Mountain-200 | Q89: =VLOOKUP(R89:R176,'col-dim'!A$2:B$3,2,TRUE) -> Col-1 | R89: Black | S89: 42 | T89: 4 | U89: 1252 | V89: 2295 | W89: 4172 | X89: =T89*U89 -> 5008 | Y89: =T89*V89 -> 9180

Sheet country_dim
A1: Country | B1: Country_Id
A2: Australia | B2: C-101
A3: Canada | B3: C-102
A4: France | B4: C-103
A5: Germany | B5: C-104
A6: United Kingdom | B6: C-105
A7: United States | B7: C-106

Sheet state_dim
A1: State | B1: State_Id
A2: British Columbia | B2: S-101
A3: California | B3: S-102
A4: England | B4: S-103
A5: Hamburg | B5: S-104
A6: Hessen | B6: S-105
A7: New South Wales | B7: S-106
A8: Nord | B8: S-107
A9: Nordrhein-Westfalen | B9: S-108
A10: Oregon | B10: S-109
A11: Queensland | B11: S-110
A12: Seine (Paris) | B12: S-111
... A18: Washington | B18: S-117

Sheet col-dim
A1: Color | B1: Color_id
A2: Black | B2: Col-1
A3: Silver | B3: Col-2

Sheet model_dim
A1: Model | B1: Model_id
A2: Mountain-100 | B2: M-101
A3: Mountain-200 | B3: M-102
A4: Mountain-400-W | B4: M-103
A5: Mountain-500 | B5: M-104

Sheet revenue_fact table
A1: Sales_Order # | B1: Date | C1: Day | D1: Month | E1: Year | F1: Country_id | G1: State_id | H1: Model_id | I1: Color_id | J1: Size | K1: Order_Quantity | L1: Unit_Cost | M1: Unit_Price | N1: Profit | O1: Cost | P1: Revenue
A2: 261695 | B2: 44531 | C2: 1 | D2: December | E2: 2021 | F2: C-106 | G2: S-102 | H2: M-102 | I2: Col-1 | J2: 46 | K2: 4 | L2: 1252 | M2: 2295 | N2: 4172 | O2: =K2*L2 -> 5008 | P2: =K2*M2 -> 9180
A3: 261696 | B3: 44531 | C3: 1 | D3: December | E3: 2021 | F3: C-105 | G3: S-103 | H3: M-102 | I3: Col-2 | J3: 42 | K3: 1 | L3: 1266 | M3: 2320 | N3: 1054 | O3: =K3*L3 -> 1266 | P3: =K3*M3 -> 2320
A4: 261697 | B4: 44532 | C4: 2 | D4: December | E4: 2021 | F4: C-106 | G4: S-102 | H4: M-103 | I4: Col-2 | J4: 46 | K4: 2 | L4: 420 | M4: 769 | N4: 698 | O4: =K4*L4 -> 840 | P4: =K4*M4 -> 1538
A5: 261698 | B5: 44532 | C5: 2 | D5: December | E5: 2021 | F5: C-101 | G5: S-106 | H5: M-103 | I5: Col-2 | J5: 42 | K5: 1 | L5: 420 | M5: 769 | N5: 349 | O5: =K5*L5 -> 420 | P5: =K5*M5 -> 769
A6: 261699 | B6: 44533 | C6: 3 | D6: December | E6: 2021 | F6: C-106 | G6: S-102 | H6: M-102 | I6: Col-1 | J6: 46 | K6: 2 | L6: 1252 | M6: 2295 | N6: 2086 | O6: =K6*L6 -> 2504 | P6: =K6*M6 -> 4590
A7: 261700 | B7: 44533 | C7: 3 | D7: December | E7: 2021 | F7: C-105 | G7: S-103 | H7: M-102 | I7: Col-1 | J7: 38 | K7: 1 | L7: 1252 | M7: 2295 | N7: 1043 | O7: =K7*L7 -> 1252 | P7: =K7*M7 -> 2295
A8: 261701 | B8: 44533 | C8: 3 | D8: December | E8: 2021 | F8: C-106 | G8: S-117 | H8: M-102 | I8: Col-1 | J8: 46 | K8: 1 | L8: 1252 | M8: 2295 | N8: 1043 | O8: =K8*L8 -> 1252 | P8: =K8*M8 -> 2295
A9: 261702 | B9: 44534 | C9: 4 | D9: December | E9: 2021 | F9: C-101 | G9: S-106 | H9: M-103 | I9: Col-2 | J9: 42 | K9: 4 | L9: 420 | M9: 769 | N9: 1396 | O9: =K9*L9 -> 1680 | P9: =K9*M9 -> 3076
A10: 261703 | B10: 44535 | C10: 5 | D10: December | E10: 2021 | F10: C-106 | G10: S-102 | H10: M-102 | I10: Col-1 | J10: 46 | K10: 4 | L10: 1252 | M10: 2295 | N10: 4172 | O10: =K10*L10 -> 5008 | P10: =K10*M10 -> 9180
A11: 261704 | B11: 44535 | C11: 5 | D11: December | E11: 2021 | F11: C-104 | G11: S-108 | H11: M-102 | I11: Col-1 | J11: 38 | K11: 4 | L11: 1252 | M11: 2295 | N11: 4172 | O11: =K11*L11 -> 5008 | P11: =K11*M11 -> 9180
A12: 261705 | B12: 44535 | C12: 5 | D12: December | E12: 2021 | F12: C-101 | G12: S-110 | H12: M-102 | I12: Col-2 | J12: 38 | K12: 1 | L12: 1266 | M12: 2320 | N12: 1054 | O12: =K12*L12 -> 1266 | P12: =K12*M12 -> 2320
A13: 261706 | B13: 44535 | C13: 5 | D13: December | E13: 2021 | F13: C-106 | G13: S-102 | H13: M-102 | I13: Col-1 | J13: 46 | K13: 1 | L13: 1252 | M13: 2295 | N13: 1043 | O13: =K13*L13 -> 1252 | P13: =K13*M13 -> 2295
... A89: 261782 | B89: 44554 | C89: 24 | D89: December | E89: 2021 | F89: C-101 | G89: S-110 | H89: M-102 | I89: Col-1 | J89: 42 | K89: 4 | L89: 1252 | M89: 2295 | N89: 4172 | O89: =K89*L89 -> 5008 | P89: =K89*M89 -> 9180

Sheet dirty data
A1: Sales_Order # | B1: Date | C1: Day | D1: Month | E1: Year | F1: Customer_Age | G1: Age_Group | H1: Customer_Gender | I1: Country | J1: State | K1: Product_Category | L1: Sub_Category | M1: Model | N1: Color | O1: Size | P1: Order_Quantity | Q1: Unit_Cost | R1: Unit_Price | S1: Profit | T1: Cost | U1: Revenue
A2: 000261695 | B2: 44531 | C2: 1 | D2: December | E2: 2021 | F2: 39 | G2: Adults (35-64) | H2: Female | I2: United States | J2: California | K2: Bikes | L2: Mountain Bikes | M2: Mountain-200 | N2: Black | O2: 46 | P2: 4 | Q2: 1252 | R2: 2295 | S2: 4172 | T2: =P2*Q2 -> 5008 | U2: =P2*R2 -> 9180
A3: 000261696 | B3: 44531 | C3: 1 | D3: December | E3: 2021 | F3: 44 | G3: Adults (35-64) | H3: Male | I3: United Kingdom | J3: England | K3: Bikes | L3: Mountain Bikes | M3: Mountain-200 | N3: Silver | O3: 42 | P3: 1 | Q3: 1266 | R3: 2320 | S3: 1054 | T3: =P3*Q3 -> 1266 | U3: =P3*R3 -> 2320
A4: 000261697 | B4: 44532 | C4: 2 | D4: December | E4: 2021 | F4: 37 | G4: Adults (35-64) | H4: Male | I4: United States | J4: California | K4: Bikes | L4: Mountain Bikes | M4: Mountain-400-W | N4: Silver | O4: 46 | P4: 2 | Q4: 420 | R4: 769 | S4: 698 | T4: =P4*Q4 -> 840 | U4: =P4*R4 -> 1538
A5: 000261698 | B5: 44532 | C5: 2 | D5: December | E5: 2021 | F5: 31 | G5: Young Adults (25-34) | H5: Female | I5: Australia | J5: New South Wales | K5: Bikes | L5: Mountain Bikes | M5: Mountain-400-W | N5: Silver | O5: 42 | P5: 1 | Q5: 420 | R5: 769 | S5: 349 | T5: =P5*Q5 -> 420 | U5: =P5*R5 -> 769
A6: 000261699 | B6: 44533 | C6: 3 | D6: December | E6: 2021 | F6: 37 | G6: Adults (35-64) | H6: Female | I6: United States | J6: California | K6: Bikes | L6: Mountain Bikes | M6: Mountain-200 | N6: Black | O6: 46 | P6: 2 | Q6: 1252 | R6: 2295 | S6: 2086 | T6: =P6*Q6 -> 2504 | U6: =P6*R6 -> 4590
A7: 000261700 | B7: 44533 | C7: 3 | D7: December | E7: 2021 | F7: 24 | G7: Youth (<25) | H7: Female | I7: United Kingdom | J7: England | K7: Bikes | L7: Mountain Bikes | M7: Mountain-200 | N7: Black | O7: 38 | P7: 1 | Q7: 1252 | R7: 2295 | S7: 1043 | T7: =P7*Q7 -> 1252 | U7: =P7*R7 -> 2295
A8: 000261701 | B8: 44533 | C8: 3 | D8: December | E8: 2021 | F8: 37 | G8: Adults (35-64) | H8: Male | I8: United States | J8: Washington | K8: Bikes | L8: Mountain Bikes | M8: Mountain-200 | N8: Black | O8: 46 | P8: 1 | Q8: 1252 | R8: 2295 | S8: 1043 | T8: =P8*Q8 -> 1252 | U8: =P8*R8 -> 2295
A9: 000261702 | B9: 44534 | C9: 4 | D9: December | E9: 2021 | F9: 31 | G9: Young Adults (25-34) | H9: Female | I9: Australia | J9: New South Wales | K9: Bikes | L9: Mountain Bikes | M9: Mountain-400-W | N9: Silver | O9: 42 | P9: 4 | Q9: 420 | R9: 769 | S9: 1396 | T9: =P9*Q9 -> 1680 | U9: =P9*R9 -> 3076
A10: 000261703 | B10: 44535 | C10: 5 | D10: December | E10: 2021 | F10: 39 | G10: Adults (35-64) | H10: Female | I10: United States | J10: California | K10: Bikes | L10: Mountain Bikes | M10: Mountain-200 | N10: Black | O10: 46 | P10: 4 | Q10: 1252 | R10: 2295 | S10: 4172 | T10: =P10*Q10 -> 5008 | U10: =P10*R10 -> 9180
A11: 000261704 | B11: 44535 | C11: 5 | D11: December | E11: 2021 | F11: 42 | G11: Adults (35-64) | H11: Male | I11: Germany | J11: Nordrhein-Westfalen | K11: Bikes | L11: Mountain Bikes | M11: Mountain-200 | N11: Black | O11: 38 | P11: 4 | Q11: 1252 | R11: 2295 | S11: 4172 | T11: =P11*Q11 -> 5008 | U11: =P11*R11 -> 9180
A12: 000261705 | B12: 44535 | C12: 5 | D12: December | E12: 2021 | F12: 35 | G12: Adults (35-64) | H12: Female | I12: Australia | J12: Queensland | K12: Bikes | L12: Mountain Bikes | M12: Mountain-200 | N12: Silver | O12: 38 | P12: 1 | Q12: 1266 | R12: 2320 | S12: 1054 | T12: =P12*Q12 -> 1266 | U12: =P12*R12 -> 2320
A13: 000261706 | B13: 44535 | C13: 5 | D13: December | E13: 2021 | F13: 37 | G13: Adults (35-64) | H13: Female | I13: United States | J13: California | K13: Bikes | L13: Mountain Bikes | M13: Mountain-200 | N13: Black | O13: 46 | P13: 1 | Q13: 1252 | R13: 2295 | S13: 1043 | T13: =P13*Q13 -> 1252 | U13: =P13*R13 -> 2295
... A89: 000261782 | B89: 44554 | C89: 24 | D89: December | E89: 2021 | F89: 38 | G89: Adults (35-64) | H89: Male | I89: Australia | J89: Queensland | K89: Bikes | L89: Mountain Bikes | M89: Mountain-200 | N89: Black | O89: 42 | P89: 4 | Q89: 1252 | R89: 2295 | S89: 4172 | T89: =P89*Q89 -> 5008 | U89: =P89*R89 -> 9180
